README.rst
setup.py
wedo/__init__.py
wedo/distance.py
wedo/motor.py
wedo/tilt.py
wedo.egg-info/PKG-INFO
wedo.egg-info/SOURCES.txt
wedo.egg-info/dependency_links.txt
wedo.egg-info/not-zip-safe
wedo.egg-info/requires.txt
wedo.egg-info/top_level.txt
wedo_plugin/__init__.py
wedo_plugin/wedo_plugin.py
wedo_plugin/wedo/__init__.py
wedo_plugin/wedo/distance.py
wedo_plugin/wedo/motor.py
wedo_plugin/wedo/tilt.py