Metadata-Version: 1.1
Name: wedo
Version: 1.1.0
Summary: This is a python library for the Lego WeDo, a tethered-over-USB sensing and robotics toolkit produced by Lego for the educational market.
Home-page: https://github.com/gbin/WeDoMore
Author: Guillaume BINET
Author-email: gbin@gootz.net
License: GPL
Keywords: lego wedo motor tilt sensor driver
Platform: UNKNOWN
Classifier: Development Status :: 5 - Production/Stable
Classifier: Intended Audience :: Education
Classifier: License :: OSI Approved :: GNU General Public License v2 (GPLv2)
Classifier: Operating System :: POSIX :: Linux
Classifier: Programming Language :: Python :: 2
Classifier: Programming Language :: Python :: 2.7
Classifier: Programming Language :: Python :: 3
Classifier: Programming Language :: Python :: 3.2
